{
  "root": {
    "id": "SYSTEM",
    "sample_system": "Cu-Al",
    "sort_mode": "name"
  },
  "nodes": [
    {
      "id": "2de1e9",
      "parent": "SYSTEM",
      "class": "Wafer",
      "entry_created_date": "20251111_174350",
      "properties": {
        "material": "Cu reference",
        "substrate": "Si",
        "film_thickness": "3 um"
      }
    },
    {
      "id": "3760ab",
      "parent": "SYSTEM",
      "class": "Wafer",
      "entry_created_date": "20251111_174437",
      "properties": {
        "material": "Cu-Al5 reference",
        "substrate": "Si",
        "film_thickness": "3.2 um",
        "note": "SN1",
        "deposition_temperature": "150 C"
      }
    },
    {
      "id": "0ddf8e",
      "parent": "SYSTEM",
      "class": "Wafer",
      "entry_created_date": "20251111_174108",
      "properties": {
        "material": "Cu-Al10 reference",
        "substrate": "Si/Si3N4",
        "film_thickness": "3.2 um",
        "note": "Amit \"Sample-3\"",
        "deposition_date": "27.11.22"
      }
    },
    {
      "id": "ffd37e",
      "parent": "SYSTEM",
      "class": "Chip",
      "entry_created_date": "20251111_175445",
      "properties": {
        "material": "CuAlAl calibration",
        "deposition_date": "26.03.2025",
        "deposition_time": "15 min",
        "note": "35 cycles ALD on top"
      }
    },
    {
      "id": "b4044d",
      "parent": "ffd37e",
      "class": "SEM_stub",
      "entry_created_date": "20251111_175938",
      "properties": {
        "stub_diameter": "12.7 mm"
      }
    },
    {
      "id": "ff4d5d",
      "parent": "SYSTEM",
      "class": "Chip",
      "entry_created_date": "20251111_181804",
      "properties": {
        "material": "CuAlAl calibration #2",
        "deposition_date": "30.05.2025"
      }
    },
    {
      "id": "6e36d6",
      "parent": "ff4d5d",
      "class": "SEM_stub",
      "entry_created_date": "20251111_181823",
      "properties": {
        "stub_diameter": "12.7 mm"
      }
    },
    {
      "id": "2372d4",
      "parent": "SYSTEM",
      "class": "Wafer",
      "entry_created_date": "20251112_154105",
      "properties": {
        "material": "Cu-Al10 60nm",
        "film_thickness": "3.2 um",
        "substrate": "Si/Si3N4",
        "deposition_temperature": "150",
        "<New property...>": ""
      }
    },
    {
      "id": "75736c",
      "parent": "2372d4",
      "class": "Chip",
      "entry_created_date": "20251112_154320",
      "properties": {}
    },
    {
      "id": "13f0fb",
      "parent": "2372d4",
      "class": "Chip",
      "entry_created_date": "20251112_154410",
      "properties": {
        "note": "\"extra\""
      }
    },
    {
      "id": "494c54",
      "parent": "SYSTEM",
      "class": "Wafer",
      "entry_created_date": "20251112_154548",
      "properties": {
        "material": "Cu-Al10 40nm",
        "substrate": "Si/Si3N4",
        "film_thickness": "3.2 um",
        "deposition_temperature": "RT"
      }
    },
    {
      "id": "f4b626",
      "parent": "494c54",
      "class": "Chip",
      "entry_created_date": "20251112_154602",
      "properties": {}
    },
    {
      "id": "d2243a",
      "parent": "494c54",
      "class": "Chip",
      "entry_created_date": "20251112_154618",
      "properties": {
        "note": "\"extra\""
      }
    },
    {
      "id": "50e811",
      "parent": "0ddf8e",
      "class": "Chip",
      "entry_created_date": "20251112_154937",
      "properties": {}
    },
    {
      "id": "e186c2",
      "parent": "0ddf8e",
      "class": "Chip",
      "entry_created_date": "20251112_155215",
      "properties": {
        "note": "\"extra\""
      }
    },
    {
      "id": "33d34f",
      "parent": "SYSTEM",
      "class": "Wafer",
      "entry_created_date": "20251112_155340",
      "properties": {
        "material": "Cu-Al10 120nm",
        "film_thickness": "3.2 um",
        "deposition_temperature": "150"
      }
    },
    {
      "id": "b087fb",
      "parent": "33d34f",
      "class": "Chip",
      "entry_created_date": "20251112_155417",
      "properties": {
        "note": "\"Extra\""
      }
    },
    {
      "id": "7e71ca",
      "parent": "2de1e9",
      "class": "Chip",
      "entry_created_date": "20251112_155603",
      "properties": {
        "note": "\"Sample 1\""
      }
    },
    {
      "id": "93d643",
      "parent": "2de1e9",
      "class": "Chip",
      "entry_created_date": "20251112_155648",
      "properties": {
        "note": "\"extra\""
      }
    },
    {
      "id": "bdfbcf",
      "parent": "SYSTEM",
      "class": "Wafer",
      "entry_created_date": "20251112_160058",
      "properties": {
        "material": "Cu/Cu-Al10 60nm",
        "film_thickness": "3.2 um",
        "deposition_temperature": "RT"
      }
    },
    {
      "id": "defb3e",
      "parent": "bdfbcf",
      "class": "Chip",
      "entry_created_date": "20251112_160112",
      "properties": {}
    },
    {
      "id": "f75ce0",
      "parent": "SYSTEM",
      "class": "Chip",
      "entry_created_date": "20251112_161807",
      "properties": {
        "material": "CuCuAl PVD",
        "deposition_date": "21.03.2025",
        "deposition_time": "15 min",
        "note": "ALD on top"
      }
    },
    {
      "id": "fc59b2",
      "parent": "SYSTEM",
      "class": "Wafer",
      "entry_created_date": "20251112_162210",
      "properties": {
        "material": "Cu/Cu-Al10 180nm",
        "deposition_date": "20.02.2025",
        "note": "1 layer of each; accidental PVD Cu + ALD monolayer at start",
        "deposition_temperature": "RT",
        "name": "aborted"
      }
    },
    {
      "id": "a7a857",
      "parent": "SYSTEM",
      "class": "Wafer",
      "entry_created_date": "20251112_162443",
      "properties": {
        "material": "Cu/Cu-Al10 106nm",
        "deposition_date": "21.02.2025",
        "film_thickness": "1.9 um",
        "note": "planned to be 180nm"
      }
    },
    {
      "id": "4a61a8",
      "parent": "a7a857",
      "class": "Chip",
      "entry_created_date": "20251112_162754",
      "properties": {}
    },
    {
      "id": "95d2f7",
      "parent": "SYSTEM",
      "class": "Wafer",
      "entry_created_date": "20251112_163001",
      "properties": {
        "material": "Cu/Cu-Al10 180nm",
        "deposition_date": "22.02.2025",
        "deposition_temperature": "RT"
      }
    },
    {
      "id": "07342d",
      "parent": "SYSTEM",
      "class": "Wafer",
      "entry_created_date": "20251112_163204",
      "properties": {
        "material": "Cu/Cu-Al10 40nm",
        "deposition_date": "26.02.2025",
        "deposition_temperature": "RT"
      }
    },
    {
      "id": "8b86ba",
      "parent": "SYSTEM",
      "class": "Chip",
      "entry_created_date": "20251112_163507",
      "properties": {
        "material": "Cu calibration",
        "deposition_time": "15 min",
        "deposition_date": "03.04.2025",
        "note": "2x6mm Cu, 150mA"
      }
    },
    {
      "id": "79b90a",
      "parent": "SYSTEM",
      "class": "Chip",
      "entry_created_date": "20251112_164317",
      "properties": {
        "material": "Cu-Al10/Cu calibration",
        "deposition_time": "10 min",
        "note": "300mA Cu; 100mA Al",
        "deposition_date": "30.10.2024"
      }
    },
    {
      "id": "b491be",
      "parent": "95d2f7",
      "class": "Chip",
      "entry_created_date": "20251112_173738",
      "properties": {}
    },
    {
      "id": "b21e35",
      "parent": "2de1e9",
      "class": "Chip",
      "entry_created_date": "20251112_175310",
      "properties": {}
    },
    {
      "id": "P9d6dd",
      "parent": "b21e35",
      "class": "Annealing",
      "entry_created_date": "20251112_175349",
      "properties": {
        "temperature_C": "310",
        "duration": "2 hrs",
        "annealing_date": "09.10.2024"
      }
    },
    {
      "id": "2a45a8",
      "parent": "2de1e9",
      "class": "Chip",
      "entry_created_date": "20251112_175543",
      "properties": {}
    },
    {
      "id": "P44547",
      "parent": "2a45a8",
      "class": "Annealing",
      "entry_created_date": "20251112_175624",
      "properties": {
        "temperature_C": "460",
        "duration": "2 hrs",
        "annealing_date": "09.10.2024"
      }
    },
    {
      "id": "26317e",
      "parent": "2de1e9",
      "class": "Chip",
      "entry_created_date": "20251112_175757",
      "properties": {}
    },
    {
      "id": "P9b95e",
      "parent": "26317e",
      "class": "Annealing",
      "entry_created_date": "20251112_175827",
      "properties": {
        "temperature_C": "550",
        "duration": "2 hrs",
        "annealing_date": "22.10.2024"
      }
    },
    {
      "id": "21776d",
      "parent": "SYSTEM",
      "class": "Wafer",
      "entry_created_date": "20251112_180051",
      "properties": {
        "material": "Cu 60nm"
      }
    },
    {
      "id": "16d205",
      "parent": "21776d",
      "class": "Chip",
      "entry_created_date": "20251112_160131",
      "properties": {}
    },
    {
      "id": "14f6b3",
      "parent": "21776d",
      "class": "Chip",
      "entry_created_date": "20251112_180101",
      "properties": {}
    },
    {
      "id": "Pabf80",
      "parent": "14f6b3",
      "class": "Annealing",
      "entry_created_date": "20251112_180125",
      "properties": {
        "temperature_C": "310",
        "duration": "2 hrs",
        "annealing_date": "14.10.2024"
      }
    },
    {
      "id": "1f27f7",
      "parent": "21776d",
      "class": "Chip",
      "entry_created_date": "20251112_180248",
      "properties": {}
    },
    {
      "id": "Pf3b7b",
      "parent": "1f27f7",
      "class": "Annealing",
      "entry_created_date": "20251112_180304",
      "properties": {
        "temperature_C": "460",
        "duration": "2 hrs",
        "annealing_date": "23.10.2024"
      }
    },
    {
      "id": "705394",
      "parent": "0ddf8e",
      "class": "Chip",
      "entry_created_date": "20251112_180530",
      "properties": {}
    },
    {
      "id": "P8e4c5",
      "parent": "705394",
      "class": "Annealing",
      "entry_created_date": "20251112_180553",
      "properties": {
        "temperature_C": "310",
        "duration": "2 hrs",
        "annealing_date": "09.10.2024"
      }
    },
    {
      "id": "b9134d",
      "parent": "0ddf8e",
      "class": "Chip",
      "entry_created_date": "20251112_180701",
      "properties": {}
    },
    {
      "id": "Pa408c",
      "parent": "b9134d",
      "class": "Annealing",
      "entry_created_date": "20251112_180723",
      "properties": {
        "temperature_C": "460",
        "duration": "2 hrs",
        "annealing_date": "09.10.2024"
      }
    },
    {
      "id": "6eaac8",
      "parent": "2372d4",
      "class": "Chip",
      "entry_created_date": "20251112_180844",
      "properties": {}
    },
    {
      "id": "P964c5",
      "parent": "6eaac8",
      "class": "Annealing",
      "entry_created_date": "20251112_180904",
      "properties": {
        "temperature_C": "310",
        "duration": "2 hrs",
        "annealing_date": "09.10.2024"
      }
    },
    {
      "id": "713b6a",
      "parent": "2372d4",
      "class": "Chip",
      "entry_created_date": "20251112_181033",
      "properties": {}
    },
    {
      "id": "Pf6c24",
      "parent": "713b6a",
      "class": "Annealing",
      "entry_created_date": "20251112_181058",
      "properties": {
        "temperature_C": "460",
        "duration": "2 hrs",
        "annealing_date": "09.10.2024"
      }
    },
    {
      "id": "0a7d3d",
      "parent": "33d34f",
      "class": "Chip",
      "entry_created_date": "20251112_181442",
      "properties": {}
    },
    {
      "id": "Pd0a3a",
      "parent": "0a7d3d",
      "class": "Annealing",
      "entry_created_date": "20251112_181516",
      "properties": {
        "temperature_C": "310",
        "duration": "2 hrs",
        "annealing_date": "14.10.2025"
      }
    },
    {
      "id": "eb3501",
      "parent": "494c54",
      "class": "Chip",
      "entry_created_date": "20251112_181639",
      "properties": {}
    },
    {
      "id": "P42aef",
      "parent": "eb3501",
      "class": "Annealing",
      "entry_created_date": "20251112_181704",
      "properties": {
        "temperature_C": "460",
        "duration": "2 hrs",
        "annealing_date": "23.10.2024"
      }
    },
    {
      "id": "261cba",
      "parent": "494c54",
      "class": "Chip",
      "entry_created_date": "20251112_182026",
      "properties": {}
    },
    {
      "id": "P84ded",
      "parent": "261cba",
      "class": "Annealing",
      "entry_created_date": "20251112_182043",
      "properties": {
        "temperature_C": "550",
        "duration": "2 hrs",
        "annealing_date": "31.10.2024"
      }
    },
    {
      "id": "37d83a",
      "parent": "bdfbcf",
      "class": "Chip",
      "entry_created_date": "20251112_182326",
      "properties": {}
    },
    {
      "id": "Pbc0a7",
      "parent": "37d83a",
      "class": "Annealing",
      "entry_created_date": "20251112_182409",
      "properties": {
        "temperature_C": "310",
        "duration": "2 hrs",
        "annealing_date": "02.04.2025"
      }
    },
    {
      "id": "131861",
      "parent": "bdfbcf",
      "class": "Chip",
      "entry_created_date": "20251112_182440",
      "properties": {}
    },
    {
      "id": "Pdfab7",
      "parent": "131861",
      "class": "Annealing",
      "entry_created_date": "20251112_182458",
      "properties": {
        "temperature_C": "310",
        "duration": "2 hrs",
        "annealing_date": "10.07.2025"
      }
    },
    {
      "id": "cb56cc",
      "parent": "bdfbcf",
      "class": "Chip",
      "entry_created_date": "20251112_182952",
      "properties": {}
    },
    {
      "id": "Pd183b",
      "parent": "cb56cc",
      "class": "Annealing",
      "entry_created_date": "20251112_183010",
      "properties": {
        "temperature_C": "460",
        "duration": "2 hrs",
        "annealing_date": "02.04.2025"
      }
    },
    {
      "id": "580c88",
      "parent": "bdfbcf",
      "class": "Chip",
      "entry_created_date": "20251112_183108",
      "properties": {}
    },
    {
      "id": "P31eb0",
      "parent": "580c88",
      "class": "Annealing",
      "entry_created_date": "20251112_183140",
      "properties": {
        "temperature_C": "550",
        "duration": "2 hrs",
        "annealing_date": "01.04.2025"
      }
    },
    {
      "id": "1644dc",
      "parent": "494c54",
      "class": "Chip",
      "entry_created_date": "20251113_121919",
      "properties": {}
    },
    {
      "id": "Pb4f04",
      "parent": "1644dc",
      "class": "Annealing",
      "entry_created_date": "20251113_121945",
      "properties": {
        "temperature_C": "310",
        "duration": "2 hrs",
        "annealing_date": "14.10.2024"
      }
    },
    {
      "id": "c51dce",
      "parent": "Pb4f04",
      "class": "SEM_stub",
      "entry_created_date": "20251113_122004",
      "properties": {
        "stub_diameter": "12.7 mm"
      }
    },
    {
      "id": "aeba83",
      "parent": "c51dce",
      "class": "Pillar_array",
      "entry_created_date": "20251113_122039",
      "properties": {
        "No_pillars": "6"
      }
    },
    {
      "id": "P813c5",
      "parent": "aeba83",
      "class": "Micromechanical_testing",
      "entry_created_date": "20251113_122116",
      "properties": {
        "test_type": "micropillar compression",
        "testing_date": "13.11.2025",
        "strain_rate": "1e-3"
      }
    },
    {
      "id": "dfdc5d",
      "parent": "Pf3b7b",
      "class": "SEM_stub",
      "entry_created_date": "20251113_160954",
      "properties": {
        "stub_diameter": "12.7 mm"
      }
    },
    {
      "id": "514901",
      "parent": "dfdc5d",
      "class": "Pillar_array",
      "entry_created_date": "20251113_161015",
      "properties": {
        "No_pillars": "6"
      }
    },
    {
      "id": "P99525",
      "parent": "514901",
      "class": "Micromechanical_testing",
      "entry_created_date": "20251113_161055",
      "properties": {
        "test_type": "micropillar compression",
        "testing_date": "13.11.2025",
        "strain_rate": "1e-3"
      }
    },
    {
      "id": "a7c02c",
      "parent": "2372d4",
      "class": "Chip",
      "entry_created_date": "20251113_184857",
      "properties": {}
    },
    {
      "id": "P7daa2",
      "parent": "a7c02c",
      "class": "Annealing",
      "entry_created_date": "20251113_184934",
      "properties": {
        "temperature_C": "550",
        "duration": "2 hrs",
        "annealing_date": "18.10.2024"
      }
    },
    {
      "id": "7071b4",
      "parent": "P7daa2",
      "class": "SEM_stub",
      "entry_created_date": "20251113_185007",
      "properties": {
        "stub_diameter": "1 in"
      }
    },
    {
      "id": "10b5f7",
      "parent": "7071b4",
      "class": "Pillar_array",
      "entry_created_date": "20251113_185056",
      "properties": {
        "No_pillars": "6"
      }
    },
    {
      "id": "P3588e",
      "parent": "10b5f7",
      "class": "Micromechanical_testing",
      "entry_created_date": "20251113_185743",
      "properties": {
        "test_type": "micropillar compression",
        "testing_date": "27.10.2025",
        "strain_rate": "1e-3"
      }
    },
    {
      "id": "eded35",
      "parent": "P44547",
      "class": "SEM_stub",
      "entry_created_date": "20251113_193339",
      "properties": {
        "stub_diameter": "12.7 mm",
        "note": "stub shared with another sample"
      }
    },
    {
      "id": "3f30ee",
      "parent": "eded35",
      "class": "Pillar_array",
      "entry_created_date": "20251113_193402",
      "properties": {}
    },
    {
      "id": "Pbf54a",
      "parent": "3f30ee",
      "class": "Micromechanical_testing",
      "entry_created_date": "20251113_193430",
      "properties": {
        "test_type": "micropillar compression",
        "testing_date": "26.02.2025",
        "strain_rate": "1e-3"
      }
    },
    {
      "id": "28c2ef",
      "parent": "P9d6dd",
      "class": "SEM_stub",
      "entry_created_date": "20251113_193452",
      "properties": {
        "stub_diameter": "12.7 mm"
      }
    },
    {
      "id": "26d1d2",
      "parent": "28c2ef",
      "class": "Pillar_array",
      "entry_created_date": "20251113_193522",
      "properties": {}
    },
    {
      "id": "P1b3a2",
      "parent": "26d1d2",
      "class": "Micromechanical_testing",
      "entry_created_date": "20251113_193548",
      "properties": {
        "test_type": "micropillar compression",
        "strain_rate": "1e-3",
        "testing_date": "25.02.2025"
      }
    },
    {
      "id": "161aca",
      "parent": "P8e4c5",
      "class": "SEM_stub",
      "entry_created_date": "20251113_193620",
      "properties": {
        "stub_diameter": "12.7 mm"
      }
    },
    {
      "id": "102c6a",
      "parent": "161aca",
      "class": "Pillar_array",
      "entry_created_date": "20251113_193627",
      "properties": {}
    },
    {
      "id": "P0a1e8",
      "parent": "102c6a",
      "class": "Micromechanical_testing",
      "entry_created_date": "20251113_193701",
      "properties": {
        "test_type": "micropillar compression",
        "strain_rate": "1e-3",
        "testing_date": "26.02.2025"
      }
    },
    {
      "id": "741d73",
      "parent": "Pd0a3a",
      "class": "SEM_stub",
      "entry_created_date": "20251113_193752",
      "properties": {
        "stub_diameter": "12.7 mm"
      }
    },
    {
      "id": "581a21",
      "parent": "741d73",
      "class": "Pillar_array",
      "entry_created_date": "20251113_193804",
      "properties": {}
    },
    {
      "id": "Pf3fde",
      "parent": "581a21",
      "class": "Micromechanical_testing",
      "entry_created_date": "20251113_193823",
      "properties": {
        "test_type": "micropillar compression",
        "strain_rate": "1e-3",
        "testing_date": "26.02.2025"
      }
    },
    {
      "id": "edfc3f",
      "parent": "Pf6c24",
      "class": "SEM_stub",
      "entry_created_date": "20251113_193956",
      "properties": {
        "stub_diameter": "12.7 mm"
      }
    },
    {
      "id": "1c8499",
      "parent": "edfc3f",
      "class": "Pillar_array",
      "entry_created_date": "20251113_194002",
      "properties": {}
    },
    {
      "id": "P0342c",
      "parent": "1c8499",
      "class": "Micromechanical_testing",
      "entry_created_date": "20251113_194025",
      "properties": {
        "test_type": "micropillar compression",
        "strain_rate": "1e-3",
        "testing_date": "26.02.2025"
      }
    },
    {
      "id": "9b3ca0",
      "parent": "Pa408c",
      "class": "SEM_stub",
      "entry_created_date": "20251113_194123",
      "properties": {
        "stub_diameter": "12.7 mm",
        "note": "shared stub with Cu ref 450C eded35"
      }
    },
    {
      "id": "7c75ea",
      "parent": "9b3ca0",
      "class": "Pillar_array",
      "entry_created_date": "20251113_194130",
      "properties": {}
    },
    {
      "id": "P9eced",
      "parent": "7c75ea",
      "class": "Micromechanical_testing",
      "entry_created_date": "20251113_194216",
      "properties": {
        "test_type": "micropillar compression",
        "strain_rate": "1e-3",
        "testing_date": "26.02.2025"
      }
    },
    {
      "id": "f58071",
      "parent": "P964c5",
      "class": "SEM_stub",
      "entry_created_date": "20251113_194259",
      "properties": {
        "stub_diameter": "12.7 mm"
      }
    },
    {
      "id": "7f14de",
      "parent": "f58071",
      "class": "Pillar_array",
      "entry_created_date": "20251113_194318",
      "properties": {}
    },
    {
      "id": "P569ee",
      "parent": "7f14de",
      "class": "Micromechanical_testing",
      "entry_created_date": "20251113_194407",
      "properties": {
        "test_type": "micropillar compression",
        "strain_rate": "1e-3",
        "testing_date": "25.02.2025"
      }
    },
    {
      "id": "891d48",
      "parent": "P42aef",
      "class": "SEM_stub",
      "entry_created_date": "20251113_210427",
      "properties": {
        "stub_diameter": "12.7 mm"
      }
    },
    {
      "id": "ed7805",
      "parent": "891d48",
      "class": "Pillar_array",
      "entry_created_date": "20251113_210501",
      "properties": {
        "No_pillars": "15"
      }
    },
    {
      "id": "P12fd5",
      "parent": "ed7805",
      "class": "Imaging",
      "entry_created_date": "20251113_210623",
      "properties": {
        "microscope": "Mira",
        "note": "only very thin coating of film"
      }
    },
    {
      "id": "8490d1",
      "parent": "P9b95e",
      "class": "SEM_stub",
      "entry_created_date": "20251113_210826",
      "properties": {
        "stub_diameter": "18 mm"
      }
    },
    {
      "id": "1b51e5",
      "parent": "8490d1",
      "class": "Pillar_array",
      "entry_created_date": "20251113_215027",
      "properties": {
        "No_pillars": "6"
      }
    },
    {
      "id": "P81545",
      "parent": "1b51e5",
      "class": "Micromechanical_testing",
      "entry_created_date": "20251113_215053",
      "properties": {
        "test_type": "micropillar compression",
        "strain_rate": "1e-3",
        "testing_date": "13.11.2025"
      }
    },
    {
      "id": "a43375",
      "parent": "0ddf8e",
      "class": "Chip",
      "entry_created_date": "20251114_130141",
      "properties": {}
    },
    {
      "id": "P0f470",
      "parent": "a43375",
      "class": "Annealing",
      "entry_created_date": "20251114_130200",
      "properties": {
        "temperature_C": "550",
        "duration": "2 hrs",
        "annealing_date": "24.10.2024"
      }
    },
    {
      "id": "27832e",
      "parent": "P0f470",
      "class": "SEM_stub",
      "entry_created_date": "20251114_130235",
      "properties": {
        "stub_diameter": "25.4 mm"
      }
    },
    {
      "id": "a400d5",
      "parent": "27832e",
      "class": "Pillar_array",
      "entry_created_date": "20251114_130303",
      "properties": {
        "No_pillars": "6"
      }
    },
    {
      "id": "P27888",
      "parent": "a400d5",
      "class": "Micromechanical_testing",
      "entry_created_date": "20251114_130349",
      "properties": {
        "test_type": "micropillar compression",
        "strain_rate": "1e-3",
        "testing_date": "14.11.2025"
      }
    },
    {
      "id": "5be6ac",
      "parent": "21776d",
      "class": "Chip",
      "entry_created_date": "20251114_130711",
      "properties": {}
    },
    {
      "id": "P00ca5",
      "parent": "5be6ac",
      "class": "Annealing",
      "entry_created_date": "20251114_130740",
      "properties": {
        "temperature_C": "550",
        "duration": "2 hrs",
        "annealing_date": "18.10.2024"
      }
    },
    {
      "id": "4d419a",
      "parent": "P00ca5",
      "class": "SEM_stub",
      "entry_created_date": "20251114_130753",
      "properties": {
        "stub_diameter": "25.4 mm"
      }
    },
    {
      "id": "7ee321",
      "parent": "4d419a",
      "class": "Pillar_array",
      "entry_created_date": "20251114_130855",
      "properties": {
        "No_pillars": "6"
      }
    },
    {
      "id": "Pba2b4",
      "parent": "7ee321",
      "class": "Micromechanical_testing",
      "entry_created_date": "20251114_130834",
      "properties": {
        "test_type": "micropillar compressiojn",
        "strain_rate": "1e-3",
        "testing_date": "14.11.2025"
      }
    },
    {
      "id": "be4f46",
      "parent": "33d34f",
      "class": "Chip",
      "entry_created_date": "20251114_132416",
      "properties": {}
    },
    {
      "id": "P8c098",
      "parent": "be4f46",
      "class": "Annealing",
      "entry_created_date": "20251114_132426",
      "properties": {
        "temperature_C": "460",
        "duration": "2 hrs",
        "annealing_date": "15.10.2024"
      }
    },
    {
      "id": "d94abb",
      "parent": "P8c098",
      "class": "SEM_stub",
      "entry_created_date": "20251114_132623",
      "properties": {
        "stub_diameter": "12.7 mm",
        "note": "only thin coating left"
      }
    },
    {
      "id": "7d0260",
      "parent": "d94abb",
      "class": "Pillar_array",
      "entry_created_date": "20251114_132631",
      "properties": {
        "No_pillars": "6"
      }
    },
    {
      "id": "dfdefb",
      "parent": "33d34f",
      "class": "Chip",
      "entry_created_date": "20251114_133021",
      "properties": {}
    },
    {
      "id": "P9cfda",
      "parent": "dfdefb",
      "class": "Annealing",
      "entry_created_date": "20251114_133114",
      "properties": {
        "temperature_C": "550",
        "duration": "2 hrs",
        "annealing_date": "11.07.2025"
      }
    },
    {
      "id": "aef115",
      "parent": "P9cfda",
      "class": "SEM_stub",
      "entry_created_date": "20251114_133151",
      "properties": {
        "stub_diameter": "18 mm"
      }
    },
    {
      "id": "74a30c",
      "parent": "aef115",
      "class": "Pillar_array",
      "entry_created_date": "20251114_133252",
      "properties": {
        "No_pillars": "6"
      }
    },
    {
      "id": "Pa1f00",
      "parent": "74a30c",
      "class": "Micromechanical_testing",
      "entry_created_date": "20251114_133317",
      "properties": {
        "test_type": "micropillar compression",
        "strain_rate": "1e-3",
        "testing_date": "14.11.2025"
      }
    },
    {
      "id": "2bc33b",
      "parent": "93d643",
      "class": "Chip",
      "entry_created_date": "20251116_153831",
      "properties": {
        "note": "given to Jonas"
      }
    },
    {
      "id": "3ae4e9",
      "parent": "21776d",
      "class": "Chip",
      "entry_created_date": "20251124_100725",
      "properties": {}
    },
    {
      "id": "Pe25ee",
      "parent": "3ae4e9",
      "class": "Annealing",
      "entry_created_date": "20251124_100808",
      "properties": {
        "temperature_C": "310",
        "duration": "2 hrs",
        "annealing_date": "10.07.2025"
      }
    },
    {
      "id": "57dc57",
      "parent": "Pe25ee",
      "class": "SEM_stub",
      "entry_created_date": "20251124_100824",
      "properties": {
        "stub_diameter": "25.4 mm"
      }
    },
    {
      "id": "c162f6",
      "parent": "57dc57",
      "class": "Pillar_array",
      "entry_created_date": "20251124_133927",
      "properties": {
        "No_pillars": "6"
      }
    },
    {
      "id": "P00399",
      "parent": "c162f6",
      "class": "FIB_milling",
      "entry_created_date": "20251124_134435",
      "properties": {
        "ion_species": "Ga",
        "microscope": "Lyra New"
      }
    },
    {
      "id": "cf4d5e",
      "parent": "891d48",
      "class": "Pillar_array",
      "entry_created_date": "20251124_160314",
      "properties": {
        "No_pillars": "6"
      }
    },
    {
      "id": "P0a5ef",
      "parent": "cf4d5e",
      "class": "FIB_milling",
      "entry_created_date": "20251124_160450",
      "properties": {
        "ion_species": "Ga",
        "microscope": "Lyra New",
        "milling_date": "24.11.2025"
      }
    },
    {
      "id": "4f1ff9",
      "parent": "aef115",
      "class": "Pillar_array",
      "entry_created_date": "20251124_192447",
      "properties": {
        "No_pillars": "6"
      }
    },
    {
      "id": "P9ef38",
      "parent": "4f1ff9",
      "class": "FIB_milling",
      "entry_created_date": "20251124_192504",
      "properties": {
        "ion_species": "Ga",
        "microscope": "Lyra New",
        "milling_date": "24.11.2025"
      }
    },
    {
      "id": "P78d39",
      "parent": "c162f6",
      "class": "Micromechanical_testing",
      "entry_created_date": "20251127_215240",
      "properties": {
        "test_type": "micropillar compression",
        "strain_rate": "1e-3",
        "testing_date": "27.11.2025"
      }
    },
    {
      "id": "P4b4b8",
      "parent": "7d0260",
      "class": "Micromechanical_testing",
      "entry_created_date": "20251127_215324",
      "properties": {
        "test_type": "micropillar compression",
        "strain_rate": "1e-3",
        "testing_date": "27.11.2025"
      }
    },
    {
      "id": "P12072",
      "parent": "cf4d5e",
      "class": "Micromechanical_testing",
      "entry_created_date": "20251127_215427",
      "properties": {
        "test_type": "micropillar compression",
        "strain_rate": "1e-3",
        "testing_date": "27.11.2025"
      }
    },
    {
      "id": "P2ea4d",
      "parent": "a400d5",
      "class": "Liftout",
      "entry_created_date": "20251201_172141",
      "properties": {
        "ion_species": "Ga+",
        "microscope": "Lyra New",
        "liftout_date": "30.11.2025",
        "liftout_location": "pillar_03"
      }
    },
    {
      "id": "7553d4",
      "parent": "P2ea4d",
      "class": "TEM_lamella",
      "entry_created_date": "20251201_172245",
      "properties": {
        "grid_material": "Mo",
        "grid_post": "B",
        "grid_ID": "Gb23f7"
      }
    },
    {
      "id": "P432dd",
      "parent": "1b51e5",
      "class": "Liftout",
      "entry_created_date": "20251201_172410",
      "properties": {
        "ion_species": "Ga+",
        "microscope": "Lyra New",
        "liftout_date": "30.11.2025",
        "liftout_location": "pillar_03"
      }
    },
    {
      "id": "a24b4c",
      "parent": "P432dd",
      "class": "TEM_lamella",
      "entry_created_date": "20251201_172437",
      "properties": {
        "grid_material": "Mo",
        "grid_post": "A",
        "grid_ID": "Gb23f7"
      }
    },
    {
      "id": "Pb5194",
      "parent": "7ee321",
      "class": "Liftout",
      "entry_created_date": "20251201_172657",
      "properties": {
        "ion_species": "Ga+",
        "microscope": "Lyra New",
        "liftout_date": "01.12.2025",
        "liftout_location": "pillar_03"
      }
    },
    {
      "id": "bcface",
      "parent": "Pb5194",
      "class": "TEM_lamella",
      "entry_created_date": "20251201_172723",
      "properties": {
        "grid_material": "Mo",
        "grid_ID": "Gb23f7",
        "grid_post": "A"
      }
    },
    {
      "id": "9b71e6",
      "parent": "8490d1",
      "class": "Pillar_array",
      "entry_created_date": "20251204_103359",
      "properties": {
        "No_pillars": "6"
      }
    },
    {
      "id": "P8dc89",
      "parent": "9b71e6",
      "class": "FIB_milling",
      "entry_created_date": "20251204_110238",
      "properties": {
        "ion_species": "Ga+",
        "microscope": "Lyra New",
        "milling_date": "04.12.2025",
        "FIB_currents": "2nA, 1nA"
      }
    },
    {
      "id": "5e9bff",
      "parent": "dfdc5d",
      "class": "Pillar_array",
      "entry_created_date": "20251204_140819",
      "properties": {
        "No_pillars": "6"
      }
    },
    {
      "id": "Pa703c",
      "parent": "5e9bff",
      "class": "FIB_milling",
      "entry_created_date": "20251204_140845",
      "properties": {
        "ion_species": "Ga+",
        "microscope": "Lyra New",
        "FIB_currents": "5nA, 1nA, 140pA",
        "milling_date": "04.12.2025"
      }
    },
    {
      "id": "21dce3",
      "parent": "27832e",
      "class": "Pillar_array",
      "entry_created_date": "20251204_174930",
      "properties": {
        "No_pillars": "6"
      }
    },
    {
      "id": "P18265",
      "parent": "21dce3",
      "class": "FIB_milling",
      "entry_created_date": "20251204_175048",
      "properties": {
        "ion_species": "Ga+",
        "microscope": "Lyra New",
        "milling_date": "04.12.2025",
        "FIB_currents": "2nA, 1nA, 140pA"
      }
    },
    {
      "id": "P13ffa",
      "parent": "9b71e6",
      "class": "Micromechanical_testing",
      "entry_created_date": "20251218_113202",
      "properties": {
        "test_type": "micropillar compression",
        "strain_rate": "1e-3",
        "testing_date": "10.12.2025",
        "microscope": "XL-30"
      }
    },
    {
      "id": "P0a010",
      "parent": "21dce3",
      "class": "Micromechanical_testing",
      "entry_created_date": "20251218_113308",
      "properties": {
        "test_type": "micropillar compression",
        "strain_rate": "1e-3",
        "testing_date": "11.12.2025",
        "microscope": "XL-30"
      }
    },
    {
      "id": "P10798",
      "parent": "5e9bff",
      "class": "Micromechanical_testing",
      "entry_created_date": "20251218_113426",
      "properties": {
        "test_type": "micropillar compression",
        "strain_rate": "1e-3",
        "microscope": "XL-30",
        "testing_date": "11.12.2025"
      }
    },
    {
      "id": "0a1082",
      "parent": "95d2f7",
      "class": "Chip",
      "entry_created_date": "20260113_143953",
      "properties": {
        "wafer_location": "centre"
      }
    },
    {
      "id": "bd0667",
      "parent": "07342d",
      "class": "Chip",
      "entry_created_date": "20260113_144043",
      "properties": {
        "wafer_location": "centre"
      }
    },
    {
      "id": "e74a99",
      "parent": "0a1082",
      "class": "SEM_stub",
      "entry_created_date": "20260113_144148",
      "properties": {
        "stub_diameter": "12.7 mm"
      }
    },
    {
      "id": "eacf4c",
      "parent": "bd0667",
      "class": "SEM_stub",
      "entry_created_date": "20260113_144231",
      "properties": {
        "stub_diameter": "12.7 mm"
      }
    },
    {
      "id": "P52d4a",
      "parent": "b491be",
      "class": "Imaging",
      "entry_created_date": "20260113_144346",
      "properties": {
        "microscope": "Lyra Old",
        "imaging_date": "24.02.2025",
        "note": "total thickness 3361nm: implies 187nm layers"
      }
    },
    {
      "id": "P60239",
      "parent": "4a61a8",
      "class": "Imaging",
      "entry_created_date": "20260113_145355",
      "properties": {
        "microscope": "Hitachi S-4800",
        "imaging_date": "22.02.2025"
      }
    },
    {
      "id": "Pb6beb",
      "parent": "b491be",
      "class": "Imaging",
      "entry_created_date": "20260113_145456",
      "properties": {
        "microscope": "Hitachi S-4800",
        "imaging_date": "24.02.2025",
        "note": "total thickness 2250nm: implies 181nm layers"
      }
    },
    {
      "id": "8e1cc3",
      "parent": "eacf4c",
      "class": "Pillar_array",
      "entry_created_date": "20260113_150228",
      "properties": {
        "No_pillars": "6"
      }
    },
    {
      "id": "P8890a",
      "parent": "8e1cc3",
      "class": "FIB_milling",
      "entry_created_date": "20260113_150758",
      "properties": {
        "ion_species": "Xe",
        "microscope": "ScopeM Hydra",
        "milling_date": "24.06.2025",
        "note": "recipe optimisation. fine cuts"
      }
    },
    {
      "id": "7e68b2",
      "parent": "e74a99",
      "class": "Pillar_array",
      "entry_created_date": "20260113_151102",
      "properties": {
        "No_pillars": "18"
      }
    },
    {
      "id": "P15db0",
      "parent": "7e68b2",
      "class": "FIB_milling",
      "entry_created_date": "20260113_151125",
      "properties": {
        "ion_species": "Xe",
        "microscope": "ScopeM Hydra",
        "milling_date": "14.07.2025",
        "note": "fine cut"
      }
    },
    {
      "id": "f67358",
      "parent": "0a1082",
      "class": "SEM_stub",
      "entry_created_date": "20260113_151212",
      "properties": {
        "stub_diameter": "12.7 mm"
      }
    },
    {
      "id": "59b289",
      "parent": "bd0667",
      "class": "SEM_stub",
      "entry_created_date": "20260113_151310",
      "properties": {
        "stub_diameter": "12.7 mm"
      }
    },
    {
      "id": "da7e50",
      "parent": "f4b626",
      "class": "Chip",
      "entry_created_date": "20260120_111526",
      "properties": {}
    },
    {
      "id": "4bda59",
      "parent": "75736c",
      "class": "Chip",
      "entry_created_date": "20260120_111848",
      "properties": {}
    },
    {
      "id": "c838a5",
      "parent": "e186c2",
      "class": "Chip",
      "entry_created_date": "20260120_112030",
      "properties": {}
    },
    {
      "id": "f65c9a",
      "parent": "7e71ca",
      "class": "Chip",
      "entry_created_date": "20260120_112155",
      "properties": {}
    },
    {
      "id": "18a278",
      "parent": "defb3e",
      "class": "Chip",
      "entry_created_date": "20260120_112402",
      "properties": {}
    },
    {
      "id": "97fd31",
      "parent": "b087fb",
      "class": "Chip",
      "entry_created_date": "20260120_112544",
      "properties": {}
    },
    {
      "id": "3606fd",
      "parent": "16d205",
      "class": "Chip",
      "entry_created_date": "20260120_113057",
      "properties": {}
    },
    {
      "id": "c1c1a0",
      "parent": "SYSTEM",
      "class": "Wafer",
      "entry_created_date": "20260121_161327",
      "properties": {
        "material": "Cu-Al5 120nm",
        "deposition_temperature": "150 C",
        "note": "SN8",
        "substrate": "Si/Si3N4"
      }
    },
    {
      "id": "026841",
      "parent": "c1c1a0",
      "class": "Chip",
      "entry_created_date": "20260121_161336",
      "properties": {}
    },
    {
      "id": "a12549",
      "parent": "026841",
      "class": "Chip",
      "entry_created_date": "20260121_161506",
      "properties": {}
    },
    {
      "id": "439e80",
      "parent": "3760ab",
      "class": "Chip",
      "entry_created_date": "20260121_161631",
      "properties": {}
    },
    {
      "id": "308099",
      "parent": "3760ab",
      "class": "Chip",
      "entry_created_date": "20260121_161756",
      "properties": {
        "note": "extra"
      }
    },
    {
      "id": "b5e8b2",
      "parent": "308099",
      "class": "Chip",
      "entry_created_date": "20260121_161957",
      "properties": {}
    },
    {
      "id": "d183d2",
      "parent": "SYSTEM",
      "class": "Wafer",
      "entry_created_date": "20260121_162246",
      "properties": {
        "material": "Cu-Al5 60nm",
        "deposition_temperature": "150 C",
        "note": "SN6",
        "substrate": "Si/Si3N4"
      }
    },
    {
      "id": "15ad9f",
      "parent": "d183d2",
      "class": "Chip",
      "entry_created_date": "20260121_162257",
      "properties": {}
    },
    {
      "id": "fc73ec",
      "parent": "15ad9f",
      "class": "Chip",
      "entry_created_date": "20260121_162338",
      "properties": {}
    },
    {
      "id": "P6a5f5",
      "parent": "7e68b2",
      "class": "FIB_milling",
      "entry_created_date": "20260126_095650",
      "properties": {
        "ion_species": "Ga",
        "microscope": "Lyra New",
        "milling_date": "17.01.2026",
        "note": "fine milling, polishing",
        "FIB_currents": "150 pA"
      }
    },
    {
      "id": "P1f4fe",
      "parent": "8e1cc3",
      "class": "FIB_milling",
      "entry_created_date": "20260126_095810",
      "properties": {
        "ion_species": "Ga",
        "microscope": "Lyra New",
        "FIB_currents": "150 pA",
        "milling_date": "17.01.2026",
        "note": "fine milling, polishing"
      }
    },
    {
      "id": "P1b7c3",
      "parent": "7e68b2",
      "class": "Micromechanical_testing",
      "entry_created_date": "20260126_100108",
      "properties": {
        "test_type": "micropillar compression",
        "strain_rate": "1e-3",
        "microscope": "XL30",
        "testing_date": "20.01.2026",
        "frame": "EMPA 1",
        "tip": "C-0142522 5um FLT"
      }
    },
    {
      "id": "P153d6",
      "parent": "8e1cc3",
      "class": "Micromechanical_testing",
      "entry_created_date": "20260126_100157",
      "properties": {
        "test_type": "micropillar compression",
        "frame": "EMPA 1",
        "microscope": "XL30",
        "strain_rate": "1e-3",
        "testing_date": "20.01.2026",
        "tip": "C-0142522 5um FLT"
      }
    },
    {
      "id": "P571ca",
      "parent": "8e1cc3",
      "class": "Imaging",
      "entry_created_date": "20260129_085633",
      "properties": {
        "microscope": "Lyra New",
        "imaging_date": "17.01.2026",
        "note": "total thickness 4.40um: implies 58nm layers"
      }
    },
    {
      "id": "P09511",
      "parent": "10b5f7",
      "class": "Liftout",
      "entry_created_date": "20260205_082309",
      "properties": {
        "ion_species": "Ga",
        "microscope": "Lyra New",
        "liftout_date": "05.02.2026",
        "liftout_location": "pillar_05"
      }
    },
    {
      "id": "4f3b06",
      "parent": "P09511",
      "class": "TEM_lamella",
      "entry_created_date": "20260205_082334",
      "properties": {
        "grid_material": "Mo",
        "grid_ID": "Gb23f7",
        "grid_post": "B"
      }
    },
    {
      "id": "e2072b",
      "parent": "13f0fb",
      "class": "Chip",
      "entry_created_date": "20260215_172359",
      "properties": {}
    },
    {
      "id": "P0c70a",
      "parent": "e2072b",
      "class": "Annealing",
      "entry_created_date": "20260215_172441",
      "properties": {
        "temperature_C": "600",
        "duration": "2 hrs",
        "annealing_atmosphere": "Hydrargon",
        "annealing_date": "15.02.2026",
        "note": "ramp 10K/s, cool 6 K/s"
      }
    },
    {
      "id": "1e90b4",
      "parent": "16d205",
      "class": "Chip",
      "entry_created_date": "20260215_172533",
      "properties": {}
    },
    {
      "id": "Pbcc20",
      "parent": "1e90b4",
      "class": "Annealing",
      "entry_created_date": "20260215_172617",
      "properties": {
        "temperature_C": "600",
        "duration": "2 hrs",
        "annealing_atmosphere": "Hydrargon 10",
        "annealing_date": "15.02.2026",
        "note": "ramp 10K/s, cool 6K/s"
      }
    },
    {
      "id": "807ed9",
      "parent": "3760ab",
      "class": "SEM_stub",
      "entry_created_date": "20260401_152522",
      "properties": {
        "stub_diameter": "12.7 mm",
        "note": "Amit stub"
      }
    },
    {
      "id": "acdd3e",
      "parent": "2de1e9",
      "class": "SEM_stub",
      "entry_created_date": "20260401_153229",
      "properties": {
        "stub_diameter": "12.7 mm",
        "note": "Amit stub"
      }
    },
    {
      "id": "10172c",
      "parent": "21776d",
      "class": "SEM_stub",
      "entry_created_date": "20260401_154626",
      "properties": {
        "stub_diameter": "12.7 mm",
        "note": "Amit's sample"
      }
    },
    {
      "id": "384eb4",
      "parent": "d183d2",
      "class": "SEM_stub",
      "entry_created_date": "20260401_155314",
      "properties": {
        "stub_diameter": "12.7 mm",
        "note": "Amit's sample. \"still HT\""
      }
    },
    {
      "id": "d7dbae",
      "parent": "d183d2",
      "class": "SEM_stub",
      "entry_created_date": "20260401_155522",
      "properties": {
        "stub_diameter": "12.7 mm",
        "note": "Amit's sample. \"pillars\""
      }
    },
    {
      "id": "f24d2e",
      "parent": "c1c1a0",
      "class": "SEM_stub",
      "entry_created_date": "20260401_155820",
      "properties": {
        "stub_diameter": "12.7 mm",
        "note": "Amit's sample. \"Pillars\""
      }
    },
    {
      "id": "99b61d",
      "parent": "SYSTEM",
      "class": "Wafer",
      "entry_created_date": "20260401_160413",
      "properties": {
        "material": "Cu-Al5 40nm"
      }
    },
    {
      "id": "013974",
      "parent": "99b61d",
      "class": "SEM_stub",
      "entry_created_date": "20260401_160726",
      "properties": {
        "stub_diameter": "12.7 mm",
        "note": "Amit's sample. \"pillar\""
      }
    },
    {
      "id": "bfc68a",
      "parent": "79b90a",
      "class": "SEM_stub",
      "entry_created_date": "20260401_161156",
      "properties": {
        "stub_diameter": "12.7 mm"
      }
    },
    {
      "id": "c3e979",
      "parent": "SYSTEM",
      "class": "Wafer",
      "entry_created_date": "20260401_161551",
      "properties": {
        "material": "Cu-Al 0-12.5% gradient",
        "layer_thickness": "250 nm",
        "note": "deposited by Skye"
      }
    },
    {
      "id": "5092fd",
      "parent": "c3e979",
      "class": "SEM_stub",
      "entry_created_date": "20260401_161604",
      "properties": {
        "stub_diameter": "12.7 mm"
      }
    },
    {
      "id": "9c82cc",
      "parent": "f24d2e",
      "class": "TEM_lamella",
      "entry_created_date": "20260409_163226",
      "properties": {
        "grid_material": "Cu",
        "grid_ID": "Gc942d"
      }
    },
    {
      "id": "646144",
      "parent": "494c54",
      "class": "Chip",
      "entry_created_date": "20260413_173109",
      "properties": {}
    },
    {
      "id": "Pdf9f4",
      "parent": "646144",
      "class": "Annealing",
      "entry_created_date": "20260413_173143",
      "properties": {
        "temperature_C": "550",
        "duration": "2 hrs",
        "annealing_date": "11.07.2025",
        "ramp_rate": "5 K/s",
        "annealing_atmosphere": "Ar"
      }
    },
    {
      "id": "3b9f68",
      "parent": "Pdf9f4",
      "class": "SEM_stub",
      "entry_created_date": "20260413_173512",
      "properties": {
        "stub_diameter": "1 in"
      }
    },
    {
      "id": "951f8f",
      "parent": "Pdf9f4",
      "class": "SEM_stub",
      "entry_created_date": "20260413_173521",
      "properties": {
        "stub_diameter": "1 in"
      }
    },
    {
      "id": "f7564d",
      "parent": "acdd3e",
      "class": "Pillar_array",
      "entry_created_date": "20260414_194044",
      "properties": {}
    },
    {
      "id": "P88a94",
      "parent": "f7564d",
      "class": "Micromechanical_testing",
      "entry_created_date": "20260414_194127",
      "properties": {
        "test_type": "micropillar compression",
        "testing_date": "02.09.2023"
      }
    },
    {
      "id": "P9a5ef",
      "parent": "f7564d",
      "class": "Liftout",
      "entry_created_date": "20260414_194231",
      "properties": {
        "ion_species": "Ga",
        "microscope": "Lyra New",
        "liftout_location": "pillar SN-8",
        "liftout_date": "04.02.2026"
      }
    },
    {
      "id": "1b5513",
      "parent": "P9a5ef",
      "class": "TEM_lamella",
      "entry_created_date": "20260414_194312",
      "properties": {
        "grid_material": "Mo",
        "grid_ID": "Gb23f7",
        "grid_post": "C"
      }
    },
    {
      "id": "Paddd9",
      "parent": "1b5513",
      "class": "Imaging",
      "entry_created_date": "20260414_194429",
      "properties": {
        "microscope": "Themis 200 G3",
        "imaging_date": "27.02.2026",
        "imaging_mode": "STEM, EDX"
      }
    },
    {
      "id": "P6dffa",
      "parent": "1b5513",
      "class": "Imaging",
      "entry_created_date": "20260414_194452",
      "properties": {
        "microscope": "Themis 200 G3",
        "imaging_date": "01.03.2026",
        "imaging_mode": "CTEM"
      }
    },
    {
      "id": "P3e5a8",
      "parent": "1b5513",
      "class": "Imaging",
      "entry_created_date": "20260414_194527",
      "properties": {
        "microscope": "Themis 200 G3",
        "imaging_date": "23.03.2026",
        "imaging_mode": "HR-STEM"
      }
    },
    {
      "id": "P02613",
      "parent": "1b5513",
      "class": "Imaging",
      "entry_created_date": "20260416_204509",
      "properties": {
        "microscope": "Themis 200 G3",
        "imaging_date": "16.04.2026",
        "imaging_mode": "NanoMEGAS"
      }
    },
    {
      "id": "P8fd78",
      "parent": "7553d4",
      "class": "Imaging",
      "entry_created_date": "20260416_205135",
      "properties": {
        "microscope": "Themis 200 G3",
        "imaging_date": "27.02.2026",
        "imaging_mode": "STEM-HAADF, STEM EDX"
      }
    },
    {
      "id": "P7f21c",
      "parent": "7553d4",
      "class": "Imaging",
      "entry_created_date": "20260416_205209",
      "properties": {
        "microscope": "Themis 200 G3",
        "imaging_date": "01.03.2026",
        "imaging_mode": "CTEM, STEM EDX"
      }
    },
    {
      "id": "P11944",
      "parent": "7553d4",
      "class": "Imaging",
      "entry_created_date": "20260416_205233",
      "properties": {
        "microscope": "Themis 200 G3",
        "imaging_date": "23.03.2026",
        "imaging_mode": "STEM HAADF"
      }
    },
    {
      "id": "P4a2f2",
      "parent": "7553d4",
      "class": "Imaging",
      "entry_created_date": "20260416_205258",
      "properties": {
        "microscope": "Themis 200 G3",
        "imaging_date": "16.04.2026",
        "imaging_mode": "NanoMEGAS"
      }
    },
    {
      "id": "P8e171",
      "parent": "4f3b06",
      "class": "Imaging",
      "entry_created_date": "20260416_205405",
      "properties": {
        "microscope": "Themis 200 G3",
        "imaging_date": "16.04.2026",
        "imaging_mode": "NanoMEGAS"
      }
    },
    {
      "id": "P85fdd",
      "parent": "4f3b06",
      "class": "Imaging",
      "entry_created_date": "20260416_205717",
      "properties": {
        "microscope": "Themis 200 G3",
        "imaging_date": "05.02.2026",
        "note": "film imaging.",
        "imaging_mode": "HAADF, CTEM"
      }
    },
    {
      "id": "P04506",
      "parent": "4f3b06",
      "class": "Imaging",
      "entry_created_date": "20260416_205755",
      "properties": {
        "microscope": "Themis 200 G3",
        "imaging_date": "06.02.2026",
        "imaging_mode": "STEM EDX"
      }
    },
    {
      "id": "Peb448",
      "parent": "4f3b06",
      "class": "Imaging",
      "entry_created_date": "20260416_205836",
      "properties": {
        "microscope": "Themis 200 G3",
        "imaging_mode": "CTEM",
        "imaging_date": "01.03.2026",
        "note": "pillar imaging"
      }
    },
    {
      "id": "Pedf64",
      "parent": "4f3b06",
      "class": "Imaging",
      "entry_created_date": "20260416_205900",
      "properties": {
        "microscope": "Themis 200 G3",
        "imaging_date": "09.04.2026",
        "imaging_mode": "CTEM"
      }
    },
    {
      "id": "P88e84",
      "parent": "a24b4c",
      "class": "Imaging",
      "entry_created_date": "20260416_210734",
      "properties": {
        "microscope": "Themis 200 G3",
        "imaging_date": "27.02.2027",
        "imaging_mode": "STEM, STEM EDX"
      }
    },
    {
      "id": "P51f7e",
      "parent": "a24b4c",
      "class": "Imaging",
      "entry_created_date": "20260416_210800",
      "properties": {
        "microscope": "Themis 200 G3",
        "imaging_date": "01.03.2026",
        "imaging_mode": "CTEM, electron diffraction"
      }
    },
    {
      "id": "P8d26f",
      "parent": "a24b4c",
      "class": "Imaging",
      "entry_created_date": "20260416_210849",
      "properties": {
        "microscope": "Themis 200 G3",
        "imaging_mode": "NanoMEGAS",
        "imaging_date": "06.04.2026"
      }
    },
    {
      "id": "044aba",
      "parent": "2372d4",
      "class": "SEM_stub",
      "entry_created_date": "20260420_094431",
      "properties": {
        "stub_diameter": "12.7 mm",
        "note": "Amit stub. (5)"
      }
    },
    {
      "id": "093962",
      "parent": "21776d",
      "class": "SEM_stub",
      "entry_created_date": "20260420_094706",
      "properties": {
        "stub_diameter": "12.7 mm",
        "note": "Amit stub (4)"
      }
    },
    {
      "id": "66f4bf",
      "parent": "093962",
      "class": "Pillar_array",
      "entry_created_date": "20260420_094746",
      "properties": {}
    },
    {
      "id": "P30bb1",
      "parent": "66f4bf",
      "class": "Liftout",
      "entry_created_date": "20260420_094838",
      "properties": {
        "ion_species": "Ga",
        "microscope": "Lyra New",
        "liftout_date": "19.04.2026",
        "liftout_location": "pillar SN-3"
      }
    },
    {
      "id": "cb98c3",
      "parent": "P30bb1",
      "class": "TEM_lamella",
      "entry_created_date": "20260420_095043",
      "properties": {
        "grid_material": "Mo",
        "grid_post": "A left",
        "grid_ID": "Ge659f"
      }
    },
    {
      "id": "4869d3",
      "parent": "494c54",
      "class": "SEM_stub",
      "entry_created_date": "20260420_095419",
      "properties": {
        "stub_diameter": "12.7 mm",
        "note": "Amit stub (11)"
      }
    },
    {
      "id": "39dc73",
      "parent": "4869d3",
      "class": "Pillar_array",
      "entry_created_date": "20260420_095446",
      "properties": {}
    },
    {
      "id": "883ece",
      "parent": "0ddf8e",
      "class": "SEM_stub",
      "entry_created_date": "20260420_095626",
      "properties": {
        "stub_diameter": "12.7 mm",
        "note": "Amit stub (2)"
      }
    },
    {
      "id": "P741bb",
      "parent": "883ece",
      "class": "Liftout",
      "entry_created_date": "20260420_095745",
      "properties": {
        "ion_species": "Ga",
        "microscope": "Lyra New",
        "liftout_location": "film",
        "liftout_date": "19.04.2026"
      }
    },
    {
      "id": "dbd0af",
      "parent": "P741bb",
      "class": "TEM_lamella",
      "entry_created_date": "20260420_095827",
      "properties": {
        "grid_material": "Mo",
        "grid_post": "B left",
        "grid_ID": "Ge659f"
      }
    },
    {
      "id": "P0b62f",
      "parent": "dbd0af",
      "class": "Imaging",
      "entry_created_date": "20260420_095933",
      "properties": {
        "microscope": "Themis 200 G3",
        "imaging_date": "19.04.2026",
        "imaging_mode": "HAADF STEM, CTEM"
      }
    },
    {
      "id": "P6e2f1",
      "parent": "cb98c3",
      "class": "Imaging",
      "entry_created_date": "20260420_100019",
      "properties": {
        "microscope": "Themis 200 G3",
        "imaging_date": "19.04.2026",
        "imaging_mode": "HAADF STEM, CTEM, EDX"
      }
    },
    {
      "id": "Pba3f6",
      "parent": "cb98c3",
      "class": "Imaging",
      "entry_created_date": "20260420_100039",
      "properties": {
        "microscope": "Themis 200 G3",
        "imaging_date": "20.04.2026",
        "imaging_mode": "STEM EDX"
      }
    },
    {
      "id": "4a4ac0",
      "parent": "2372d4",
      "class": "SEM_stub",
      "entry_created_date": "20260505_144824",
      "properties": {
        "stub_diameter": "12.7 mm",
        "note": "Amit stub S2"
      }
    },
    {
      "id": "P45851",
      "parent": "4a4ac0",
      "class": "Liftout",
      "entry_created_date": "20260505_144847",
      "properties": {
        "ion_species": "Ga",
        "microscope": "Lyra _?"
      }
    },
    {
      "id": "4bf426",
      "parent": "044aba",
      "class": "Pillar_array",
      "entry_created_date": "20260505_145634",
      "properties": {}
    },
    {
      "id": "P7bcd3",
      "parent": "4bf426",
      "class": "Liftout",
      "entry_created_date": "20260505_150113",
      "properties": {
        "ion_species": "Ga",
        "microscope": "Lyra New",
        "note": "done by Vivek"
      }
    },
    {
      "id": "65e7cf",
      "parent": "P7bcd3",
      "class": "TEM_lamella",
      "entry_created_date": "20260505_150137",
      "properties": {
        "grid_material": "Cu?"
      }
    },
    {
      "id": "P9c124",
      "parent": "65e7cf",
      "class": "Imaging",
      "entry_created_date": "20260505_150214",
      "properties": {
        "microscope": "Themis 200 G3",
        "imaging_date": "20.09.2024",
        "imaging_mode": "HAADF, CTEM"
      }
    },
    {
      "id": "910dbb",
      "parent": "093962",
      "class": "Pillar_array",
      "entry_created_date": "20260505_150430",
      "properties": {
        "No_pillars": "20"
      }
    },
    {
      "id": "P011b9",
      "parent": "910dbb",
      "class": "FIB_milling",
      "entry_created_date": "20260505_150530",
      "properties": {
        "ion_species": "Ga",
        "microscope": "Lyra Old",
        "FIB_currents": "5nA, 1nA, 200pA",
        "milling_date": "05.05.2026"
      }
    },
    {
      "id": "05b055",
      "parent": "044aba",
      "class": "Pillar_array",
      "entry_created_date": "20260505_173633",
      "properties": {
        "No_pillars": "20"
      }
    },
    {
      "id": "Pa7f69",
      "parent": "05b055",
      "class": "FIB_milling",
      "entry_created_date": "20260505_173703",
      "properties": {
        "ion_species": "Ga",
        "microscope": "Lyra Old",
        "FIB_currents": "5nA, 1nA, 200pA",
        "milling_date": "05.05.2026"
      }
    },
    {
      "id": "7b9264",
      "parent": "P7daa2",
      "class": "SEM_stub",
      "entry_created_date": "20260515_135903",
      "properties": {
        "stub_diameter": "18 mm",
        "note": "\"a\", delaminated"
      }
    },
    {
      "id": "dae0b4",
      "parent": "P8c098",
      "class": "SEM_stub",
      "entry_created_date": "20260515_140109",
      "properties": {
        "stub_diameter": "12.7 mm",
        "note": "\"c\""
      }
    },
    {
      "id": "f42d45",
      "parent": "bdfbcf",
      "class": "Chip",
      "entry_created_date": "20260515_140259",
      "properties": {}
    },
    {
      "id": "Pdb699",
      "parent": "f42d45",
      "class": "Annealing",
      "entry_created_date": "20260515_140329",
      "properties": {
        "temperature_C": "550",
        "duration": "2 hrs",
        "annealing_date": "21.10.2024"
      }
    },
    {
      "id": "8cf8e5",
      "parent": "Pdb699",
      "class": "SEM_stub",
      "entry_created_date": "20260515_140344",
      "properties": {
        "stub_diameter": "12.7 mm",
        "note": "\"b\""
      }
    },
    {
      "id": "93d84a",
      "parent": "33d34f",
      "class": "SEM_stub",
      "entry_created_date": "20260515_140522",
      "properties": {
        "stub_diameter": "12.7 mm"
      }
    },
    {
      "id": "11aa86",
      "parent": "Pabf80",
      "class": "SEM_stub",
      "entry_created_date": "20260515_140733",
      "properties": {
        "stub_diameter": "12.7 mm",
        "note": "only a few layers left"
      }
    },
    {
      "id": "7a9761",
      "parent": "95d2f7",
      "class": "SEM_stub",
      "entry_created_date": "20260515_141305",
      "properties": {
        "stub_diameter": "12.7 mm",
        "note": "\"B\""
      }
    },
    {
      "id": "ea2809",
      "parent": "07342d",
      "class": "SEM_stub",
      "entry_created_date": "20260515_141546",
      "properties": {
        "stub_diameter": "12.7 mm",
        "note": "\"B\""
      }
    },
    {
      "id": "ee779d",
      "parent": "P8c098",
      "class": "SEM_stub",
      "entry_created_date": "20260515_141707",
      "properties": {
        "stub_diameter": "12.7 mm",
        "note": "\"b\""
      }
    },
    {
      "id": "a6bce5",
      "parent": "Pbc0a7",
      "class": "SEM_stub",
      "entry_created_date": "20260515_141826",
      "properties": {
        "stub_diameter": "12.7 mm",
        "note": "almost no film left"
      }
    },
    {
      "id": "193fa8",
      "parent": "Pf6c24",
      "class": "SEM_stub",
      "entry_created_date": "20260515_141937",
      "properties": {
        "stub_diameter": "1 in",
        "note": "\"b\""
      }
    },
    {
      "id": "a50df1",
      "parent": "33d34f",
      "class": "Chip",
      "entry_created_date": "20260515_142040",
      "properties": {}
    },
    {
      "id": "Pfe360",
      "parent": "a50df1",
      "class": "Annealing",
      "entry_created_date": "20260515_142110",
      "properties": {
        "temperature_C": "550",
        "duration": "2 hrs",
        "annealing_date": "24.10.2024"
      }
    },
    {
      "id": "c8c3c4",
      "parent": "Pfe360",
      "class": "SEM_stub",
      "entry_created_date": "20260515_142119",
      "properties": {
        "stub_diameter": "1 in",
        "note": "half-delaminated"
      }
    },
    {
      "id": "e21948",
      "parent": "P8c098",
      "class": "SEM_stub",
      "entry_created_date": "20260515_142310",
      "properties": {
        "stub_diameter": "12.7 mm",
        "note": "\"x\""
      }
    },
    {
      "id": "39932f",
      "parent": "07342d",
      "class": "SEM_stub",
      "entry_created_date": "20260515_142433",
      "properties": {
        "stub_diameter": "12.7 mm",
        "note": "\"B\""
      }
    }
  ]
}